beamviz/__init__.py
beamviz/cgs.py
beamviz/egsinp.py
beamviz/visualize.py
beamviz-0.0.8.dist-info/DESCRIPTION.rst
beamviz-0.0.8.dist-info/METADATA
beamviz-0.0.8.dist-info/RECORD
beamviz-0.0.8.dist-info/WHEEL
beamviz-0.0.8.dist-info/entry_points.txt
beamviz-0.0.8.dist-info/metadata.json
beamviz-0.0.8.dist-info/top_level.txt
